adv/__init__.py
adv/broadcasters.py
adv/campaigns.py
adv/client.py
adv/dctas.py
adv/events.py
adv/exceptions.py
adv/widgets.py
advocate_sdk-0.2.0.dist-info/METADATA
advocate_sdk-0.2.0.dist-info/RECORD
advocate_sdk-0.2.0.dist-info/WHEEL
advocate_sdk-0.2.0.dist-info/top_level.txt
tests/__init__.py
tests/test_client.py
tests/test_dctas.py
tests/test_events.py
tests/test_widgets.py
