Metadata-Version: 2.1
Name: advocate-sdk
Version: 0.2.0
Summary: SDK for developing interactive widgets and more on the Advocate platform
Home-page: https://github.com/AdvocatesInc/advocate-python-sdk
Author: Advocates, Inc
Author-email: admin@adv.gg
License: Proprietary and confidential
Platform: UNKNOWN
Requires-Dist: requests (>=2.9.1)
